philINT/__init__.py
philINT/classes.py
philINT/main.py
philINT/utils.py
philINT/modules/__init__.py
philINT/modules/cms/__init__.py
philINT/modules/cms/gravatar.py
philINT/modules/cms/wordpress.py
philINT/modules/education/__init__.py
philINT/modules/education/duolingo.py
philINT/modules/games/__init__.py
philINT/modules/games/chess.py
philINT/modules/programming/__init__.py
philINT/modules/programming/github.py
philINT/modules/social_media/__init__.py
philINT/modules/social_media/imgur.py
philINT/modules/social_media/mewe.py
philINT/modules/social_media/myanimelist.py
philINT/modules/social_media/twitter.py
philINT/modules/software/__init__.py
philINT/modules/software/adobe.py
philINT-0.1a0.dist-info/LICENSE
philINT-0.1a0.dist-info/METADATA
philINT-0.1a0.dist-info/WHEEL
philINT-0.1a0.dist-info/entry_points.txt
philINT-0.1a0.dist-info/top_level.txt
philINT-0.1a0.dist-info/RECORD
