Metadata-Version: 2.1
Name: philINT
Version: 0.1a0
Summary: philINT is a library that allows OSINT investigators to retrieve and organize data from an email address or an username.
Home-page: https://github.com/ajuelosemmanuel/philINT
Author: Emmanuel Ajuelos
Author-email: ajuelosemmanuel@gmail.com
Classifier: Programming Language :: Python
Classifier: License :: OSI Approved :: GNU General Public License v3 (GPLv3)
License-File: LICENSE
Requires-Dist: iso-639
Requires-Dist: pycountry
Requires-Dist: httpx
Requires-Dist: selenium
Requires-Dist: gpxpy
Requires-Dist: folium
Requires-Dist: asyncio
Requires-Dist: pandas
